{
	"webAuditReportLines": [
		{
			"issue": "WKTLO-3599",
			"summary": "Outbound Catalogs - EOB DM Extract",
			"itcTickets": [],
			"type": "Story",
			"labels": [],
			"status": "Done",
			"developer": "",
			"requiresDesign": true,
			"designComplete": false,
			"designReviewed": false,
			"designReviewedBy": [],
			"requiresCode": true,
			"codeCommitted": false,
			"codeReviews": []
		},
		{
			"issue": "WKTLO-3600",
			"summary": "Company Standards - EOB DM Extract - Stage 1",
			"itcTickets": [],
			"type": "Story",
			"labels": [],
			"status": "Done",
			"developer": "Geranne Riego",
			"requiresDesign": true,
			"designComplete": true,
			"designReviewed": false,
			"designReviewedBy": [],
			"requiresCode": true,
			"codeCommitted": true,
			"codeReviews": [
				{
					"id": "26836",
					"title": "WKTLO-3796 Scripts for interrogating Kafka",
					"link": "https://phabricator.insight.com/D26836",
					"status": "Published",
					"closed": true,
					"author": "Edward Hodd",
					"reviewer": "Chris Scott",
					"codeReviewers": [{ "name": "Chris Scott", "status": "Accepted" }],
					"repository": {
						"name": "R236",
						"link": "https://phabricator.insight.com/source/emea-on-boarding/"
					}
				},
				{
					"id": "26993",
					"title": "WKTLO-3600: Company Standards - EOB DM Extract - Stage 1",
					"link": "https://phabricator.insight.com/D26993",
					"status": "Published",
					"closed": true,
					"author": "Geranne Riego",
					"reviewer": "Ben Ryan",
					"codeReviewers": [
						{ "name": "Ben Ryan", "status": "Accepted" },
						{ "name": "Michael Harrison", "status": "Added" }
					],
					"repository": {
						"name": "R236",
						"link": "https://phabricator.insight.com/source/emea-on-boarding/"
					}
				},
				{
					"id": "27007",
					"title": "WKTLO-3600 Fixing problem connecting to QA Kafka instances",
					"link": "https://phabricator.insight.com/D27007",
					"status": "Published",
					"closed": true,
					"author": "Edward Hodd",
					"reviewer": "Chris Imeson",
					"codeReviewers": [
						{ "name": "Ben Ryan", "status": "Added" },
						{ "name": "Chris Imeson", "status": "Accepted" },
						{ "name": "Chris Scott", "status": "Added" }
					],
					"repository": {
						"name": "R236",
						"link": "https://phabricator.insight.com/source/emea-on-boarding/"
					}
				},
				{
					"id": "27094",
					"title": "WKTLO-3600  Fixing the QA Kakfa configuration",
					"link": "https://phabricator.insight.com/D27094",
					"status": "Published",
					"closed": true,
					"author": "Edward Hodd",
					"reviewer": "Chris Scott",
					"codeReviewers": [{ "name": "Chris Scott", "status": "Accepted" }],
					"repository": {
						"name": "R236",
						"link": "https://phabricator.insight.com/source/emea-on-boarding/"
					}
				},
				{
					"id": "27096",
					"title": "WKTLO-3600  Fixing the QA Kakfa configuration",
					"link": "https://phabricator.insight.com/D27096",
					"status": "Published",
					"closed": true,
					"author": "Chris Scott",
					"reviewer": "Ben Ryan",
					"codeReviewers": [
						{ "name": "Ben Ryan", "status": "Accepted" },
						{ "name": "Edward Hodd", "status": "Added" }
					],
					"repository": {
						"name": "R236",
						"link": "https://phabricator.insight.com/source/emea-on-boarding/"
					}
				}
			]
		},
		{
			"issue": "WKTLO-3601",
			"summary": "Welcome Page - EOB DM Extract",
			"itcTickets": [],
			"type": "Story",
			"labels": [],
			"status": "Done",
			"developer": "Geranne Riego",
			"requiresDesign": true,
			"designComplete": true,
			"designReviewed": true,
			"designReviewedBy": ["Edward Hodd"],
			"requiresCode": true,
			"codeCommitted": true,
			"codeReviews": [
				{
					"id": "26527",
					"title": "WKTLO-3601 : Welcome Page - EOB DM Extract",
					"link": "https://phabricator.insight.com/D26527",
					"status": "Published",
					"closed": true,
					"author": "AdamWilliam Martirez",
					"reviewer": "Michael Harrison",
					"codeReviewers": [
						{ "name": "Ben Ryan", "status": "Accepted" },
						{ "name": "Michael Harrison", "status": "Accepted" }
					],
					"repository": {
						"name": "R236",
						"link": "https://phabricator.insight.com/source/emea-on-boarding/"
					}
				},
				{
					"id": "26557",
					"title": "WKTLO-3601 : Welcome Page - EOB DM Extract",
					"link": "https://phabricator.insight.com/D26557",
					"status": "Published",
					"closed": true,
					"author": "AdamWilliam Martirez",
					"reviewer": "Chris Scott",
					"codeReviewers": [
						{ "name": "Ben Ryan", "status": "Accepted" },
						{ "name": "Michael Harrison", "status": "Added" },
						{ "name": "Chris Scott", "status": "Accepted" }
					],
					"repository": {
						"name": "R236",
						"link": "https://phabricator.insight.com/source/emea-on-boarding/"
					}
				}
			]
		},
		{
			"issue": "WKTLO-3603",
			"summary": "Users & Roles Stg 3",
			"itcTickets": [],
			"type": "Story",
			"labels": [],
			"status": "Done",
			"developer": "Edward Hodd",
			"requiresDesign": true,
			"designComplete": true,
			"designReviewed": false,
			"designReviewedBy": [],
			"requiresCode": true,
			"codeCommitted": true,
			"codeReviews": [
				{
					"id": "26291",
					"title": "WKTLO-3603 Added Stg3 User Model",
					"link": "https://phabricator.insight.com/D26291",
					"status": "Published",
					"closed": true,
					"author": "Edward Hodd",
					"reviewer": "Ben Ryan",
					"codeReviewers": [
						{ "name": "Ben Ryan", "status": "Accepted" },
						{ "name": "Michael Harrison", "status": "Added" },
						{ "name": "Damian Manifold", "status": "Added" }
					],
					"repository": {
						"name": "R236",
						"link": "https://phabricator.insight.com/source/emea-on-boarding/"
					}
				},
				{
					"id": "26327",
					"title": "WKTLO-3603 Stage 3 User Consumption",
					"link": "https://phabricator.insight.com/D26327",
					"status": "Published",
					"closed": true,
					"author": "Edward Hodd",
					"reviewer": "Ben Ryan",
					"codeReviewers": [
						{ "name": "Ben Ryan", "status": "Accepted" },
						{ "name": "Michael Harrison", "status": "Added" },
						{ "name": "Damian Manifold", "status": "Added" }
					],
					"repository": {
						"name": "R236",
						"link": "https://phabricator.insight.com/source/emea-on-boarding/"
					}
				},
				{
					"id": "26370",
					"title": "WKTLO-3603 -- Users & Roles Stg 3, added role process classes and their tests",
					"link": "https://phabricator.insight.com/D26370",
					"status": "Published",
					"closed": true,
					"author": "Tianma Guo",
					"reviewer": "Damian Manifold",
					"codeReviewers": [{ "name": "Damian Manifold", "status": "Accepted" }],
					"repository": {
						"name": "R236",
						"link": "https://phabricator.insight.com/source/emea-on-boarding/"
					}
				},
				{
					"id": "26383",
					"title": "WKTLO-3603 - Integration test for Stg3 Roles",
					"link": "https://phabricator.insight.com/D26383",
					"status": "Published",
					"closed": true,
					"author": "Ben Ryan",
					"reviewer": "Tianma Guo",
					"codeReviewers": [{ "name": "Tianma Guo", "status": "Accepted" }],
					"repository": {
						"name": "R236",
						"link": "https://phabricator.insight.com/source/emea-on-boarding/"
					}
				},
				{
					"id": "26394",
					"title": "WKTLO-3603 - Add README with how-to for adding new streams (now that the architecture has settled down a bit)",
					"link": "https://phabricator.insight.com/D26394",
					"status": "Published",
					"closed": true,
					"author": "Ben Ryan",
					"reviewer": "Tianma Guo",
					"codeReviewers": [{ "name": "Tianma Guo", "status": "Accepted" }],
					"repository": {
						"name": "R236",
						"link": "https://phabricator.insight.com/source/emea-on-boarding/"
					}
				}
			]
		},
		{
			"issue": "WKTLO-3604",
			"summary": "B2B OCI Connection Configurations - EOB DM Extract - Stage 2/3",
			"itcTickets": [],
			"type": "Story",
			"labels": [],
			"status": "Done",
			"developer": "Stuart.Smith",
			"requiresDesign": true,
			"designComplete": false,
			"designReviewed": false,
			"designReviewedBy": [],
			"requiresCode": true,
			"codeCommitted": true,
			"codeReviews": [
				{
					"id": "26814",
					"title": "WKTLO-3604 - B2B OCI stage 1 producer",
					"link": "https://phabricator.insight.com/D26814",
					"status": "Published",
					"closed": true,
					"author": "Stuart Smith",
					"reviewer": "Chris Scott",
					"codeReviewers": [{ "name": "Chris Scott", "status": "Accepted" }],
					"repository": {
						"name": "R236",
						"link": "https://phabricator.insight.com/source/emea-on-boarding/"
					}
				},
				{
					"id": "27012",
					"title": "WKTLO-3604 B2B OCI Connection Configurations - EOB DM Extract (Fixed tests)",
					"link": "https://phabricator.insight.com/D27012",
					"status": "Published",
					"closed": true,
					"author": "Chris Scott",
					"reviewer": "Stuart Smith",
					"codeReviewers": [{ "name": "Stuart Smith", "status": "Accepted" }],
					"repository": {
						"name": "R236",
						"link": "https://phabricator.insight.com/source/emea-on-boarding/"
					}
				},
				{
					"id": "27024",
					"title": "WKTLO-3604 adding oci fields to OciConverter",
					"link": "https://phabricator.insight.com/D27024",
					"status": "Published",
					"closed": true,
					"author": "Stuart Smith",
					"reviewer": "Chris Scott",
					"codeReviewers": [{ "name": "Chris Scott", "status": "Accepted" }],
					"repository": {
						"name": "R236",
						"link": "https://phabricator.insight.com/source/emea-on-boarding/"
					}
				},
				{
					"id": "27087",
					"title": "WKTLO-3604 - B2B OCI stage 1 producer",
					"link": "https://phabricator.insight.com/D27087",
					"status": "Published",
					"closed": true,
					"author": "Chris Scott",
					"reviewer": "Stuart Smith",
					"codeReviewers": [
						{ "name": "Stuart Smith", "status": "Accepted" },
						{ "name": "Ben Ryan", "status": "Added" }
					],
					"repository": {
						"name": "R236",
						"link": "https://phabricator.insight.com/source/emea-on-boarding/"
					}
				},
				{
					"id": "27179",
					"title": "WKTLO-3604 adding stg2 and stg3 producer/consumer for b2b config",
					"link": "https://phabricator.insight.com/D27179",
					"status": "Published",
					"closed": true,
					"author": "Stuart Smith",
					"reviewer": "Satish Seeram",
					"codeReviewers": [{ "name": "Satish Seeram", "status": "Accepted" }],
					"repository": {
						"name": "R236",
						"link": "https://phabricator.insight.com/source/emea-on-boarding/"
					}
				},
				{
					"id": "27191",
					"title": "WKTLO-3604 adding stg2 and stg3 producer/consumer for b2b config",
					"link": "https://phabricator.insight.com/D27191",
					"status": "Published",
					"closed": true,
					"author": "Stuart Smith",
					"reviewer": "Satish Seeram",
					"codeReviewers": [{ "name": "Satish Seeram", "status": "Accepted" }],
					"repository": {
						"name": "R236",
						"link": "https://phabricator.insight.com/source/emea-on-boarding/"
					}
				},
				{
					"id": "27212",
					"title": "WKTLO-3604 adding stg2 and stg3 producer/consumer for b2b config",
					"link": "https://phabricator.insight.com/D27212",
					"status": "Published",
					"closed": true,
					"author": "Stuart Smith",
					"reviewer": "Sridhar Kotagiri",
					"codeReviewers": [{ "name": "Sridhar Kotagiri", "status": "Accepted" }],
					"repository": {
						"name": "R236",
						"link": "https://phabricator.insight.com/source/emea-on-boarding/"
					}
				}
			]
		},
		{
			"issue": "WKTLO-3606",
			"summary": "User Permissions - EOB DM Extract",
			"itcTickets": [],
			"type": "Story",
			"labels": [],
			"status": "Done",
			"developer": "Ryan, Ben",
			"requiresDesign": true,
			"designComplete": true,
			"designReviewed": true,
			"designReviewedBy": ["Edward Hodd"],
			"requiresCode": true,
			"codeCommitted": true,
			"codeReviews": [
				{
					"id": "26616",
					"title": "WKTLO-3606 - add PermissionXref entity/repo/retriever/test",
					"link": "https://phabricator.insight.com/D26616",
					"status": "Published",
					"closed": true,
					"author": "Ben Ryan",
					"reviewer": "Damian Manifold",
					"codeReviewers": [{ "name": "Damian Manifold", "status": "Accepted" }],
					"repository": {
						"name": "R236",
						"link": "https://phabricator.insight.com/source/emea-on-boarding/"
					}
				},
				{
					"id": "26619",
					"title": "WKTLO-3606: USPermissionName",
					"link": "https://phabricator.insight.com/D26619",
					"status": "Published",
					"closed": true,
					"author": "Damian Manifold",
					"reviewer": "Ben Ryan",
					"codeReviewers": [{ "name": "Ben Ryan", "status": "Accepted" }],
					"repository": {
						"name": "R236",
						"link": "https://phabricator.insight.com/source/emea-on-boarding/"
					}
				},
				{
					"id": "26622",
					"title": "WKTLO-3606: USPermissionName",
					"link": "https://phabricator.insight.com/D26622",
					"status": "Published",
					"closed": true,
					"author": "Ben Ryan",
					"reviewer": "Damian Manifold",
					"codeReviewers": [{ "name": "Damian Manifold", "status": "Accepted" }],
					"repository": {
						"name": "R236",
						"link": "https://phabricator.insight.com/source/emea-on-boarding/"
					}
				},
				{
					"id": "26650",
					"title": "WKTLO-3606: USPermissionName tests",
					"link": "https://phabricator.insight.com/D26650",
					"status": "Published",
					"closed": true,
					"author": "Damian Manifold",
					"reviewer": "Ben Ryan",
					"codeReviewers": [{ "name": "Ben Ryan", "status": "Accepted" }],
					"repository": {
						"name": "R236",
						"link": "https://phabricator.insight.com/source/emea-on-boarding/"
					}
				},
				{
					"id": "26652",
					"title": "WKTLO-3606 - Liquibase updates for amended ErrorLog table structure",
					"link": "https://phabricator.insight.com/D26652",
					"status": "Published",
					"closed": true,
					"author": "Ben Ryan",
					"reviewer": "Damian Manifold",
					"codeReviewers": [{ "name": "Damian Manifold", "status": "Accepted" }],
					"repository": {
						"name": "R236",
						"link": "https://phabricator.insight.com/source/emea-on-boarding/"
					}
				},
				{
					"id": "26656",
					"title": "WKTLO-3606: USPermissionName",
					"link": "https://phabricator.insight.com/D26656",
					"status": "Published",
					"closed": true,
					"author": "Damian Manifold",
					"reviewer": "Ben Ryan",
					"codeReviewers": [{ "name": "Ben Ryan", "status": "Accepted" }],
					"repository": {
						"name": "R236",
						"link": "https://phabricator.insight.com/source/emea-on-boarding/"
					}
				},
				{
					"id": "26678",
					"title": "WKTLO-3606: USPermissionName",
					"link": "https://phabricator.insight.com/D26678",
					"status": "Published",
					"closed": true,
					"author": "Damian Manifold",
					"reviewer": "Ben Ryan",
					"codeReviewers": [{ "name": "Ben Ryan", "status": "Accepted" }],
					"repository": {
						"name": "R236",
						"link": "https://phabricator.insight.com/source/emea-on-boarding/"
					}
				},
				{
					"id": "26680",
					"title": "WKTLO-3606 - UserConverter updates for Non-MyInsight",
					"link": "https://phabricator.insight.com/D26680",
					"status": "Published",
					"closed": true,
					"author": "Ben Ryan",
					"reviewer": "Damian Manifold",
					"codeReviewers": [{ "name": "Damian Manifold", "status": "Accepted" }],
					"repository": {
						"name": "R236",
						"link": "https://phabricator.insight.com/source/emea-on-boarding/"
					}
				},
				{
					"id": "26683",
					"title": "WKTLO-3606 - UserConverter tests",
					"link": "https://phabricator.insight.com/D26683",
					"status": "Published",
					"closed": true,
					"author": "Damian Manifold",
					"reviewer": "Ben Ryan",
					"codeReviewers": [{ "name": "Ben Ryan", "status": "Accepted" }],
					"repository": {
						"name": "R236",
						"link": "https://phabricator.insight.com/source/emea-on-boarding/"
					}
				}
			]
		},
		{
			"issue": "WKTLO-3608",
			"summary": "SmartTracker - EOB DM Extract",
			"itcTickets": [],
			"type": "Story",
			"labels": [],
			"status": "Done",
			"developer": "Geranne Riego",
			"requiresDesign": true,
			"designComplete": true,
			"designReviewed": false,
			"designReviewedBy": [],
			"requiresCode": true,
			"codeCommitted": true,
			"codeReviews": [
				{
					"id": "26649",
					"title": "WKTLO-3608: SmartTracker - EOB DM Extract",
					"link": "https://phabricator.insight.com/D26649",
					"status": "Published",
					"closed": true,
					"author": "AdamWilliam Martirez",
					"reviewer": "Ben Ryan",
					"codeReviewers": [
						{ "name": "Ben Ryan", "status": "Accepted" },
						{ "name": "Michael Harrison", "status": "Added" }
					],
					"repository": {
						"name": "R236",
						"link": "https://phabricator.insight.com/source/emea-on-boarding/"
					}
				},
				{
					"id": "26856",
					"title": "WKTLO-3608: SmartTracker - EOB DM Extract",
					"link": "https://phabricator.insight.com/D26856",
					"status": "Published",
					"closed": true,
					"author": "AdamWilliam Martirez",
					"reviewer": "Ben Ryan",
					"codeReviewers": [
						{ "name": "Ben Ryan", "status": "Accepted" },
						{ "name": "Michael Harrison", "status": "Added" }
					],
					"repository": {
						"name": "R236",
						"link": "https://phabricator.insight.com/source/emea-on-boarding/"
					}
				},
				{
					"id": "26892",
					"title": "WKTLO-3608: SmartTracker - EOB DM Extract",
					"link": "https://phabricator.insight.com/D26892",
					"status": "Published",
					"closed": true,
					"author": "AdamWilliam Martirez",
					"reviewer": "Ben Ryan",
					"codeReviewers": [
						{ "name": "Ben Ryan", "status": "Accepted" },
						{ "name": "Michael Harrison", "status": "Added" }
					],
					"repository": {
						"name": "R236",
						"link": "https://phabricator.insight.com/source/emea-on-boarding/"
					}
				},
				{
					"id": "27025",
					"title": "WKTLO-3608: SmartTracker - EOB DM Extract",
					"link": "https://phabricator.insight.com/D27025",
					"status": "Published",
					"closed": true,
					"author": "AdamWilliam Martirez",
					"reviewer": "Ben Ryan",
					"codeReviewers": [
						{ "name": "Chris Scott", "status": "Added" },
						{ "name": "Ben Ryan", "status": "Accepted" }
					],
					"repository": {
						"name": "R236",
						"link": "https://phabricator.insight.com/source/emea-on-boarding/"
					}
				},
				{
					"id": "27039",
					"title": "WKTLO-3608: SmartTracker - EOB DM Extract",
					"link": "https://phabricator.insight.com/D27039",
					"status": "Published",
					"closed": true,
					"author": "AdamWilliam Martirez",
					"reviewer": "Ben Ryan",
					"codeReviewers": [
						{ "name": "Chris Scott", "status": "Added" },
						{ "name": "Ben Ryan", "status": "Accepted" }
					],
					"repository": {
						"name": "R236",
						"link": "https://phabricator.insight.com/source/emea-on-boarding/"
					}
				},
				{
					"id": "27042",
					"title": "WKTLO-3608: SmartTracker - EOB DM Extract",
					"link": "https://phabricator.insight.com/D27042",
					"status": "Published",
					"closed": true,
					"author": "AdamWilliam Martirez",
					"reviewer": "Ben Ryan",
					"codeReviewers": [
						{ "name": "Ben Ryan", "status": "Accepted" },
						{ "name": "Chris Scott", "status": "Added" }
					],
					"repository": {
						"name": "R236",
						"link": "https://phabricator.insight.com/source/emea-on-boarding/"
					}
				},
				{
					"id": "27081",
					"title": "WKTLO-3608: SmartTracker - EOB DM Extract",
					"link": "https://phabricator.insight.com/D27081",
					"status": "Published",
					"closed": true,
					"author": "AdamWilliam Martirez",
					"reviewer": "Ben Ryan",
					"codeReviewers": [
						{ "name": "Ben Ryan", "status": "Accepted" },
						{ "name": "Chris Scott", "status": "Added" },
						{ "name": "Michael Harrison", "status": "Added" }
					],
					"repository": {
						"name": "R236",
						"link": "https://phabricator.insight.com/source/emea-on-boarding/"
					}
				},
				{
					"id": "27266",
					"title": "WKTLO-3608: Fixed integration test bean initialization issue due to recent changed",
					"link": "https://phabricator.insight.com/D27266",
					"status": "Published",
					"closed": true,
					"author": "AdamWilliam Martirez",
					"reviewer": "Ben Ryan",
					"codeReviewers": [
						{ "name": "Ben Ryan", "status": "Accepted" },
						{ "name": "Damian Manifold", "status": "Added" },
						{ "name": "Michael Harrison", "status": "Added" },
						{ "name": "Chris Scott", "status": "Added" }
					],
					"repository": {
						"name": "R236",
						"link": "https://phabricator.insight.com/source/emea-on-boarding/"
					}
				}
			]
		},
		{
			"issue": "WKTLO-3751",
			"summary": "Approval Routing - Stg 2",
			"itcTickets": [],
			"type": "Story",
			"labels": [],
			"status": "Done",
			"developer": "Satish.Seeram",
			"requiresDesign": true,
			"designComplete": false,
			"designReviewed": false,
			"designReviewedBy": [],
			"requiresCode": true,
			"codeCommitted": true,
			"codeReviews": [
				{
					"id": "26871",
					"title": "WKTLO-3751:Approval Routing - Stg2",
					"link": "https://phabricator.insight.com/D26871",
					"status": "Published",
					"closed": true,
					"author": "Satish Seeram",
					"reviewer": "Ben Ryan",
					"codeReviewers": [{ "name": "Ben Ryan", "status": "Accepted" }],
					"repository": {
						"name": "R236",
						"link": "https://phabricator.insight.com/source/emea-on-boarding/"
					}
				},
				{
					"id": "26937",
					"title": "WKTLO-3751:Approval Routing - Stg2 -fixed build issue",
					"link": "https://phabricator.insight.com/D26937",
					"status": "Published",
					"closed": true,
					"author": "Satish Seeram",
					"reviewer": "Stuart Smith",
					"codeReviewers": [
						{ "name": "Ben Ryan", "status": "Added" },
						{ "name": "Chris Scott", "status": "Added" },
						{ "name": "Stuart Smith", "status": "Accepted" }
					],
					"repository": {
						"name": "R236",
						"link": "https://phabricator.insight.com/source/emea-on-boarding/"
					}
				},
				{
					"id": "26943",
					"title": "WKTLO-3751 - ignoring failing WIP Integration Tests until they are finished",
					"link": "https://phabricator.insight.com/D26943",
					"status": "Published",
					"closed": true,
					"author": "Ben Ryan",
					"reviewer": "Chris Scott",
					"codeReviewers": [
						{ "name": "Satish Seeram", "status": "Added" },
						{ "name": "Chris Scott", "status": "Accepted" }
					],
					"repository": {
						"name": "R236",
						"link": "https://phabricator.insight.com/source/emea-on-boarding/"
					}
				},
				{
					"id": "26962",
					"title": "WKTLO-3751:Added FeatureBean for Stg2 Requestor and ApprovalPath",
					"link": "https://phabricator.insight.com/D26962",
					"status": "Published",
					"closed": true,
					"author": "Satish Seeram",
					"reviewer": "AdamWilliam Martirez",
					"codeReviewers": [
						{ "name": "Ben Ryan", "status": "Added" },
						{ "name": "AdamWilliam Martirez", "status": "Accepted" }
					],
					"repository": {
						"name": "R236",
						"link": "https://phabricator.insight.com/source/emea-on-boarding/"
					}
				}
			]
		},
		{
			"issue": "WKTLO-3794",
			"summary": "Approval Routing - EOB DM Extract - Approval Paths / Users",
			"itcTickets": [],
			"type": "Story",
			"labels": ["DemoAcceptance"],
			"status": "Done",
			"developer": "damian.manifold2",
			"requiresDesign": true,
			"designComplete": false,
			"designReviewed": false,
			"designReviewedBy": [],
			"requiresCode": true,
			"codeCommitted": true,
			"codeReviews": [
				{
					"id": "24919",
					"title": "WKTLO-3794: Approval Routing - EOB DM Extract - Approval Paths / Users",
					"link": "https://phabricator.insight.com/D24919",
					"status": "Published",
					"closed": true,
					"author": "Damian Manifold",
					"reviewer": "Ben Ryan",
					"codeReviewers": [{ "name": "Ben Ryan", "status": "Accepted" }],
					"repository": {
						"name": "R236",
						"link": "https://phabricator.insight.com/source/emea-on-boarding/"
					}
				},
				{
					"id": "24921",
					"title": "WKTLO-3794: Approval Routing - EOB DM Extract - Approval Paths / Users",
					"link": "https://phabricator.insight.com/D24921",
					"status": "Published",
					"closed": true,
					"author": "Damian Manifold",
					"reviewer": "Ben Ryan",
					"codeReviewers": [{ "name": "Ben Ryan", "status": "Accepted" }],
					"repository": {
						"name": "R236",
						"link": "https://phabricator.insight.com/source/emea-on-boarding/"
					}
				},
				{
					"id": "24923",
					"title": "WKTLO-3794: Approval Routing - EOB DM Extract - Approval Paths / Users",
					"link": "https://phabricator.insight.com/D24923",
					"status": "Published",
					"closed": true,
					"author": "Damian Manifold",
					"reviewer": "Ben Ryan",
					"codeReviewers": [{ "name": "Ben Ryan", "status": "Accepted" }],
					"repository": {
						"name": "R236",
						"link": "https://phabricator.insight.com/source/emea-on-boarding/"
					}
				},
				{
					"id": "24924",
					"title": "WKTLO-3794: Approval Routing - EOB DM Extract - Approval Paths / Users",
					"link": "https://phabricator.insight.com/D24924",
					"status": "Abandoned",
					"closed": true,
					"author": "Damian Manifold",
					"reviewer": "",
					"codeReviewers": [{ "name": "Ben Ryan", "status": "Resigned" }],
					"repository": {
						"name": "R236",
						"link": "https://phabricator.insight.com/source/emea-on-boarding/"
					}
				}
			]
		},
		{
			"issue": "WKTLO-3795",
			"summary": "Approval Routing - EOB DM Extract - Requestor Group Users",
			"itcTickets": [],
			"type": "Story",
			"labels": ["DemoAcceptance"],
			"status": "Done",
			"developer": "Ryan, Ben",
			"requiresDesign": true,
			"designComplete": false,
			"designReviewed": false,
			"designReviewedBy": [],
			"requiresCode": true,
			"codeCommitted": true,
			"codeReviews": [
				{
					"id": "24858",
					"title": "WKTLO-3795 - EOB Approval Routing - added Requestor Group Users conversion to existing Req Groups converter",
					"link": "https://phabricator.insight.com/D24858",
					"status": "Published",
					"closed": true,
					"author": "Ben Ryan",
					"reviewer": "Damian Manifold",
					"codeReviewers": [{ "name": "Damian Manifold", "status": "Accepted" }],
					"repository": {
						"name": "R236",
						"link": "https://phabricator.insight.com/source/emea-on-boarding/"
					}
				},
				{
					"id": "24902",
					"title": "WKTLO-3795 - EOB: Requestor Group Options conversion added to existing Req Groups converter",
					"link": "https://phabricator.insight.com/D24902",
					"status": "Published",
					"closed": true,
					"author": "Ben Ryan",
					"reviewer": "Damian Manifold",
					"codeReviewers": [{ "name": "Damian Manifold", "status": "Accepted" }],
					"repository": {
						"name": "R236",
						"link": "https://phabricator.insight.com/source/emea-on-boarding/"
					}
				},
				{
					"id": "24914",
					"title": "WKTLO-3795 - fixed Requestor Group Test",
					"link": "https://phabricator.insight.com/D24914",
					"status": "Published",
					"closed": true,
					"author": "Damian Manifold",
					"reviewer": "Ben Ryan",
					"codeReviewers": [{ "name": "Ben Ryan", "status": "Accepted" }],
					"repository": {
						"name": "R236",
						"link": "https://phabricator.insight.com/source/emea-on-boarding/"
					}
				},
				{
					"id": "24922",
					"title": "SAVEPOINT",
					"link": "https://phabricator.insight.com/D24922",
					"status": "Abandoned",
					"closed": true,
					"author": "Damian Manifold",
					"reviewer": "Ben Ryan",
					"codeReviewers": [{ "name": "Ben Ryan", "status": "Accepted" }],
					"repository": {
						"name": "R236",
						"link": "https://phabricator.insight.com/source/emea-on-boarding/"
					}
				},
				{
					"id": "24926",
					"title": "WKTLO-3795 - EOB: added Approvers table conversion, plus assorted fixes  / quality improvements",
					"link": "https://phabricator.insight.com/D24926",
					"status": "Published",
					"closed": true,
					"author": "Ben Ryan",
					"reviewer": "Damian Manifold",
					"codeReviewers": [{ "name": "Damian Manifold", "status": "Accepted" }],
					"repository": {
						"name": "R236",
						"link": "https://phabricator.insight.com/source/emea-on-boarding/"
					}
				}
			]
		}
	]
}
